MANIFEST.in
README.txt
setup.py
Indian_Speech_Lib/__init__.py
Indian_Speech_Lib/utils.py
Indian_Speech_Lib.egg-info/PKG-INFO
Indian_Speech_Lib.egg-info/SOURCES.txt
Indian_Speech_Lib.egg-info/dependency_links.txt
Indian_Speech_Lib.egg-info/requires.txt
Indian_Speech_Lib.egg-info/top_level.txt
Indian_Speech_Lib/Accuracy_Metric/acc_main.py
Indian_Speech_Lib/Accuracy_Metric/accuracyv2.py
Indian_Speech_Lib/Accuracy_Metric/automatic.txt
Indian_Speech_Lib/Accuracy_Metric/manual.txt
Indian_Speech_Lib/Accuracy_Metric/normalization.py
Indian_Speech_Lib/Audio_Quality_Classification/__init__.py
Indian_Speech_Lib/Audio_Quality_Classification/bihar_nalanda/__init__.py
Indian_Speech_Lib/Audio_Quality_Classification/bihar_nalanda/excl_http_req.py
Indian_Speech_Lib/Audio_Quality_Classification/bihar_nalanda/extract_features.py
Indian_Speech_Lib/Audio_Quality_Classification/bihar_nalanda/learn.py
Indian_Speech_Lib/Automatic_Transcripts/Readme
Indian_Speech_Lib/Automatic_Transcripts/__init__.py
Indian_Speech_Lib/Automatic_Transcripts/combine_script.py
Indian_Speech_Lib/Automatic_Transcripts/main.py
Indian_Speech_Lib/Automatic_Transcripts/script.py
Indian_Speech_Lib/Gender_Classification/__init__.py
Indian_Speech_Lib/Gender_Classification/disintegrate.py
Indian_Speech_Lib/Gender_Classification/excl_http_req.py
Indian_Speech_Lib/Gender_Classification/extract_features.py
Indian_Speech_Lib/Gender_Classification/integrate.py
Indian_Speech_Lib/Gender_Classification/learn.py
Indian_Speech_Lib/Gender_Classification/mp3_to_wav.py
Indian_Speech_Lib/Gender_Classification/output2.csv
Indian_Speech_Lib/Gender_Classification/output3.csv
Indian_Speech_Lib/Gender_Classification/readme
Indian_Speech_Lib/Silence_Removal/__init__.py
Indian_Speech_Lib/Silence_Removal/readme
Indian_Speech_Lib/Silence_Removal/sln.py
Indian_Speech_Lib/models/accept_reject
Indian_Speech_Lib/models/gender_nn