Metadata-Version: 1.0
Name: Indian-Speech-Lib
Version: 1.0.7
Summary: Useful speech recognition and transcription related library for Indian languages.
Home-page: http://pypi.python.org/pypi/Indian_Speech_Lib_v107/
Author: Mohd Wasih, Jayanth Reddy
Author-email: wasih.mohd@gmail.com
License: UNKNOWN
Platform: UNKNOWN
